amazfit_pyclient/__init__.py
amazfit_pyclient/chunked_encoder/__init__.py
amazfit_pyclient/chunked_encoder/aes.py
amazfit_pyclient/chunked_encoder/chunked_decoder.py
amazfit_pyclient/chunked_encoder/chunked_encoder.py
amazfit_pyclient/chunked_encoder/chunked_endpoint.py
amazfit_pyclient/chunked_encoder/handlers/__init__.py
amazfit_pyclient/chunked_encoder/handlers/auth_handler.py
amazfit_pyclient/chunked_encoder/handlers/base_handler.py
amazfit_pyclient/chunked_encoder/handlers/battery_handler.py
amazfit_pyclient/chunked_encoder/handlers/connection_handler.py
amazfit_pyclient/chunked_encoder/handlers/heartrate_handler.py
amazfit_pyclient/chunked_encoder/handlers/http_handler.py
amazfit_pyclient/chunked_encoder/handlers/logs_handler.py
amazfit_pyclient/chunked_encoder/handlers/steps_handler.py
amazfit_pyclient/chunked_encoder/handlers/utils/__init__.py
amazfit_pyclient/chunked_encoder/handlers/utils/weather_server.py
amazfit_pyclient/fetch/__init__.py
amazfit_pyclient/fetch/data_fetch.py
amazfit_pyclient/fetch/fetch_activity/__init__.py
amazfit_pyclient/fetch/fetch_activity/data_fetcher.py
amazfit_pyclient/fetch/fetch_logs/__init__.py
amazfit_pyclient/fetch/fetch_logs/data_fetcher.py
amazfit_pyclient/fetch/fetch_stress/__init__.py
amazfit_pyclient/fetch/fetch_stress/data_fetcher.py
amazfit_pyclient/fetch/utils/__init__.py
amazfit_pyclient/fetch/utils/csv_helper.py
amazfit_pyclient/fetch/utils/timeutils.py
amazfit_pyclient-0.2.8.dist-info/METADATA
amazfit_pyclient-0.2.8.dist-info/WHEEL
amazfit_pyclient-0.2.8.dist-info/top_level.txt
amazfit_pyclient-0.2.8.dist-info/RECORD
