Metadata-Version: 2.1
Name: amazfit-pyclient
Version: 0.2.8
Summary: Amazfit Python Client
Home-page: https://github.com/MyrikLD/amazfit_pyclient
Author: MyrikLD
Author-email: myrik260138@gmail.com
Classifier: Programming Language :: Python :: 3
Classifier: License :: OSI Approved :: MIT License
Requires-Dist: bleak
Requires-Dist: cryptography
Provides-Extra: http
Requires-Dist: httpx; extra == "http"
Requires-Dist: yarl; extra == "http"
